pytmat-0.2.0.dist-info/METADATA
pytmat-0.2.0.dist-info/WHEEL
pytmat-0.2.0.dist-info/licenses/LICENSE
pytmat/__init__.py
pytmat/pytmat.pypy311-pp73-s390x-linux-gnu.so
pytmat-0.2.0.dist-info/RECORD
